<?xml version="1.0"?>
<!DOCTYPE hibernate-mapping PUBLIC "-//Hibernate/Hibernate Mapping DTD 3.0//EN"
"http://hibernate.sourceforge.net/hibernate-mapping-3.0.dtd">
<!-- Generated 07-may-2012 8:14:17 by Hibernate Tools 3.2.1.GA -->
<hibernate-mapping>
    <class name="es.tpv_bar.persistencia.pojos.Configuracion" table="configuracion" catalog="mydb">
        <id name="id" type="int">
            <column name="id" />
            <generator class="assigned" />
        </id>
        <property name="clave" type="string">
            <column name="clave" length="45" />
        </property>
        <property name="value" type="string">
            <column name="value" length="45" />
        </property>
    </class>
</hibernate-mapping>
